setup.py
ConfigOptionParser.egg-info/PKG-INFO
ConfigOptionParser.egg-info/SOURCES.txt
ConfigOptionParser.egg-info/dependency_links.txt
ConfigOptionParser.egg-info/entry_points.txt
ConfigOptionParser.egg-info/not-zip-safe
ConfigOptionParser.egg-info/top_level.txt
configoptionparser/__init__.py