Metadata-Version: 1.0
Name: ConfigOptionParser
Version: 0.1
Summary: a version of OptionParser that allows parsing from .ini files
Home-page: http://k0s.org
Author: Jeff Hammel
Author-email: jhammel@mozilla.com
License: MPL
Keywords: ini cli
Platform: UNKNOWN
